zeno_client/__init__.py
zeno_client/client.py
zeno_client/exceptions.py
zeno_client/util.py
zeno_client-0.1.16.dist-info/LICENSE
zeno_client-0.1.16.dist-info/METADATA
zeno_client-0.1.16.dist-info/WHEEL
zeno_client-0.1.16.dist-info/RECORD
