Metadata-Version: 2.1
Name: zeno-client
Version: 0.1.16
Summary: Python client for creating new Zeno projects and uploading data.
License: MIT
Author: Zeno Team
Author-email: hello@zenoml.com
Requires-Python: >=3.8
Classifier: License :: OSI Approved :: MIT License
Classifier: Programming Language :: Python :: 3
Classifier: Programming Language :: Python :: 3.8
Classifier: Programming Language :: Python :: 3.9
Classifier: Programming Language :: Python :: 3.10
Classifier: Programming Language :: Python :: 3.11
Classifier: Programming Language :: Python :: 3.12
Requires-Dist: arrow-json (>=0.9.0,<0.10.0)
Requires-Dist: outdated (>=0.2.0)
Requires-Dist: pandas (>=1.4.3)
Requires-Dist: pyarrow (>=6.0.0)
Requires-Dist: pydantic (>=1.0)
Requires-Dist: requests (>=2.20.0)
Requires-Dist: tqdm (>=4.1.0)
